Workbook

Sheet 00W603
A1: SALES COMMISSION RECAP
A2: HIRE DATE | C2: 41029
A3: Salesman Name | C3: ADAM WEST
A4: Salesman # | C4: W603
A5: Payperiod Ending | C5: 46280
E6: COMMISSIONS
C7: DBW | D7: HELIX | E7: Miscellaneous | F7: Total
A8: Sales
B9: 46267 | C9: 227.32 | D9: 0 | E9: 0 | F9: =SUM(C9:E9) -> 227.32
B10: 46268 | C10: 202.176 | D10: 0 | E10: 0 | F10: =SUM(C10:E10) -> 202.176
B11: 46269 | C11: 361.2 | D11: 0 | E11: 0 | F11: =SUM(C11:E11) -> 361.2
B12: 46272 | C12: 0 | D12: 0 | E12: 0 | F12: =SUM(C12:E12) -> 0
B13: 46273 | C13: 0 | D13: 0 | E13: 0 | F13: =SUM(C13:E13) -> 0
B14: 46274 | C14: 1729.384 | D14: 0 | E14: 0 | F14: =SUM(C14:E14) -> 1729.384
B15: 46275 | C15: 264.02 | D15: 0 | E15: 0 | F15: =SUM(C15:E15) -> 264.02
B16: 46276 | C16: 1.38 | D16: 0 | E16: 0 | F16: =SUM(C16:E16) -> 1.38
B17: 46279 | C17: 98.38 | D17: 0 | E17: 0 | F17: =SUM(C17:E17) -> 98.38
B18: 46280 | C18: 0 | D18: 0 | E18: 0 | F18: =SUM(C18:E18) -> 0
B19: Extra 1
B20: Extra 2
B21: Extra 3
B22: Extra 4
B23: Extra 5
B24: Total | C24: =SUM(C9:C23) -> 2883.86 | D24: =SUM(D9:D23) -> 0 | E24: =SUM(E9:E23) -> 0 | F24: =SUM(F9:F23) -> 2883.86
A26: Returns
A27: Cust # | B27: Inv #
F28: 0
F29: 0
F30: 0
F31: 0
F32: =SUM(F28:F31) -> 0
A34: 120 Day Chews
A35: Cust # | B35: Inv #
F36: 0
F37: 0
F38: 0
F39: 0
F40: 0
F41: 0
F42: 0
F43: 0
F44: =SUM(F36:F43) -> 0
A45: Adjustments
A46: Cust # | B46: Inv #
F47: 0
F48: 0
F49: 0
F50: 0
F51: 0
F52: 0
F53: =SUM(F47:F52) -> 0
E57: Grand Total | F57: =+F24+F32+F44+F53 -> 2883.86
A58: Deductions on hold
A59: Reserve: | B59: 500 | C59: full

Sheet 00W762
A1: SALES COMMISSION RECAP
A2: HIRE DATE | C2: 37503
A3: Salesman Name | C3: Kerry Smith
A4: Salesman # | C4: W762
A5: Payperiod Ending | C5: ='00W603'!C5 -> 46280
E6: COMMISSIONS
C7: DBW | D7: HELIX | E7: MISC | F7: Total
A8: Sales
B9: ='00W603'!B9 -> 46267 | C9: 0 | D9: 0 | E9: 0 | F9: =SUM(C9:E9) -> 0
B10: ='00W603'!B10 -> 46268 | C10: 0 | D10: 0 | E10: 0 | F10: =SUM(C10:E10) -> 0
B11: ='00W603'!B11 -> 46269 | C11: 0 | D11: 0 | E11: 0 | F11: =SUM(C11:E11) -> 0
B12: ='00W603'!B12 -> 46272 | C12: 0 | D12: 0 | E12: 0 | F12: =SUM(C12:E12) -> 0
B13: ='00W603'!B13 -> 46273 | C13: 0 | D13: 0 | E13: 0 | F13: =SUM(C13:E13) -> 0
B14: ='00W603'!B14 -> 46274 | C14: 18 | D14: 0 | E14: 0 | F14: =SUM(C14:E14) -> 18
B15: ='00W603'!B15 -> 46275 | C15: 171.185 | D15: 0 | E15: 0 | F15: =SUM(C15:E15) -> 171.185
B16: ='00W603'!B16 -> 46276 | C16: 0 | D16: 0 | E16: 0 | F16: =SUM(C16:E16) -> 0
B17: ='00W603'!B17 -> 46279 | C17: 0 | D17: 0 | E17: 0 | F17: =SUM(C17:E17) -> 0
B18: ='00W603'!B18 -> 46280 | C18: 0 | D18: 0 | E18: 0 | F18: =SUM(C18:E18) -> 0
B19: =+'00W603'!B19 -> Extra 1
B20: =+'00W603'!B20 -> Extra 2
B21: Extra 3
B22: Extra 4
B23: Extra 5
B24: Total | C24: =SUM(C9:C23) -> 189.185 | D24: =SUM(D9:D23) -> 0 | E24: =SUM(E9:E23) -> 0 | F24: =SUM(F9:F23) -> 189.185
A26: Returns
A27: Cust # | B27: Inv #
F28: 0
F29: 0
F30: 0
F31: 0
F32: 0
F33: =SUM(F28:F32) -> 0
A35: 120 day chews
A36: Cust # | B36: Inv #
F37: 0
F38: 0
F39: 0
F40: =SUM(F37:F39) -> 0
A41: Adjustments
A42: 09/01 payroll shortfall | F42: -15.12
F43: 0
F44: 0
F45: =SUM(F42:F44) -> -15.12
E48: Grand Total | F48: =+F24+F33+F40+F45 -> 174.065
A50: Deductions on hold:

Sheet 00W784
A1: SALES COMMISSION RECAP
A2: Start Date | C2: 42375
A3: Salesman Name | C3: JUSTIN GRECO
A4: Salesman # | C4: W784
A5: Payperiod Ending | C5: =+'00W603'!C5 -> 46280
E6: COMMISSIONS
C7: DBW | D7: HELIX | E7: MISC | F7: Total
A8: Sales
B9: =+'00W603'!B9 -> 46267 | C9: 478.0528 | D9: 0 | E9: 0 | F9: =SUM(C9:E9) -> 478.0528
B10: =+'00W603'!B10 -> 46268 | C10: 202.176 | D10: 0 | E10: 0 | F10: =SUM(C10:E10) -> 202.176
B11: =+'00W603'!B11 -> 46269 | C11: 272.1164 | D11: 0 | E11: 0 | F11: =SUM(C11:E11) -> 272.1164
B12: =+'00W603'!B12 -> 46272 | C12: 0 | D12: 0 | E12: 0 | F12: =SUM(C12:E12) -> 0
B13: =+'00W603'!B13 -> 46273 | C13: 825.96 | D13: 0 | E13: 0 | F13: =SUM(C13:E13) -> 825.96
B14: ='00W603'!B14 -> 46274 | C14: 0 | D14: 0 | E14: 0 | F14: =SUM(C14:E14) -> 0
B15: ='00W603'!B15 -> 46275 | C15: 0 | D15: 0 | E15: 0 | F15: =SUM(C15:E15) -> 0
B16: ='00W603'!B16 -> 46276 | C16: 712.05 | D16: 0 | E16: 0 | F16: =SUM(C16:E16) -> 712.05
B17: ='00W603'!B17 -> 46279 | C17: 84.8 | D17: 0 | E17: 0 | F17: =SUM(C17:E17) -> 84.8
B18: ='00W603'!B18 -> 46280 | C18: 0 | D18: 0 | E18: 0 | F18: =SUM(C18:E18) -> 0
B19: =+'00W603'!B19 -> Extra 1
B20: =+'00W603'!B20 -> Extra 2
B21: =+'00W603'!B21 -> Extra 3
B22: =+'00W603'!B22 -> Extra 4
B23: Total | C23: =SUM(C9:C22) -> 2575.1552 | D23: =SUM(D9:D22) -> 0 | E23: =SUM(E9:E22) -> 0 | F23: =SUM(F9:F22) -> 2575.1552
A25: Returns
A26: Cust # | B26: Inv #
A27: MID4444 | B27: 633991 | F27: -253.14
F28: 0
F29: 0
F30: 0
F31: 0
F32: =SUM(F27:F31) -> -253.14
A34: 120 day chews
A35: Cust # | B35: Inv #
F36: 0
F37: 0
F38: 0
F39: 0
F40: =SUM(F36:F39) -> 0
A41: Adjustments
A42: 9/3 spiff | F42: 100
F43: 0
F44: 0
F45: 0
F46: =SUM(F42:F45) -> 100
E49: Grand Total | F49: =+F23+F32+F40+F46 -> 2422.0152
A52: Reserve | B52: FULL
A57: Deductions on hold

Sheet 00W839
A1: SALES COMMISSION RECAP
A2: HIRE DATE | C2: 42830
A3: Salesman Name | C3: RONALD BONICH
A4: Salesman # | C4: W839
A5: Payperiod Ending | C5: ='00W603'!C5 -> 46280
E6: COMMISSIONS
C7: DBW | D7: HELIX | E7: HELIX TOOLS | F7: Total
A8: Sales
B9: ='00W603'!B9 -> 46267 | C9: -93.96 | D9: 0 | E9: 0 | F9: =SUM(C9:E9) -> -93.96
B10: =+'00W603'!B10 -> 46268 | C10: 0 | D10: 0 | E10: 0 | F10: =SUM(C10:E10) -> 0
B11: ='00W603'!B11 -> 46269 | C11: 323.81 | D11: 0 | E11: 0 | F11: =SUM(C11:E11) -> 323.81
B12: ='00W603'!B12 -> 46272 | C12: 0 | D12: 0 | E12: 0 | F12: =SUM(C12:E12) -> 0
B13: ='00W603'!B13 -> 46273 | C13: 1158.42 | D13: 0 | E13: 0 | F13: =SUM(C13:E13) -> 1158.42
B14: ='00W603'!B14 -> 46274 | C14: 0 | D14: 0 | E14: 0 | F14: =SUM(C14:E14) -> 0
B15: ='00W603'!B15 -> 46275 | C15: 0 | D15: 0 | E15: 0 | F15: =SUM(C15:E15) -> 0
B16: ='00W603'!B16 -> 46276 | C16: 0 | D16: 0 | E16: 0 | F16: =SUM(C16:E16) -> 0
B17: ='00W603'!B17 -> 46279 | C17: 0 | D17: 0 | E17: 0 | F17: =SUM(C17:E17) -> 0
B18: ='00W603'!B18 -> 46280 | C18: 0 | D18: 0 | E18: 0 | F18: =SUM(C18:E18) -> 0
B19: =+'00W603'!B19 -> Extra 1
B20: =+'00W603'!B20 -> Extra 2
B21: Extra 3
B22: Extra 4
B23: Extra 5
B24: Total | C24: =SUM(C9:C23) -> 1388.27 | D24: =SUM(D9:D23) -> 0 | E24: =SUM(E9:E23) -> 0 | F24: =SUM(F9:F23) -> 1388.27
A26: Returns
A27: Cust # | B27: Inv #
F28: 0
F29: 0
F30: 0
F31: =SUM(F28:F30) -> 0
A33: 120 Day Chews
A34: Cust # | B34: Inv #
F35: 0
F36: 0
F37: 0
F38: 0
F39: =SUM(F35:F38) -> 0
A40: Adjustments
A41: Cust # | B41: Inv #
F42: 0
F43: 0
F44: 0
F45: 0
F46: 0
F47: 0
F48: 0
F49: 0
F50: =SUM(F42:F49) -> 0
E54: Grand Total | F54: =+F24+F31+F39+F50 -> 1388.27
A57: Reserve: | B57: FULL
A61: Guarantee
A62: 7.25
B63: Hours | C63: Pay | D63: Hours | E63: Pay
B64: Week1 | C64: Week1 | D64: Week2 | E64: Week2 | F64: Total
A65: Regular | B65: 0 | C65: =A62*B65 -> 0 | D65: 0 | E65: =+D65*A62 -> 0 | F65: =+C65+E65 -> 0
A66: Overtime | B66: 0 | C66: =A62*B66*1.5 -> 0 | D66: 0 | E66: =A62*D66*1.5 -> 0 | F66: =+C66+E66 -> 0
A67: Total | B67: =+B65+B66 -> 0 | C67: =+C65+C66 -> 0 | D67: =+D65+D66 -> 0 | E67: =+E65+E66 -> 0 | F67: =+F65+F66 -> 0
A69: Deductions on Hold
A70: SCE2026 | B70: 623446 | C70: hold payment plan | E70: (39% unpaid) | F70: -689.9925

Sheet 00W909
A1: SALES COMMISSION RECAP
A2: HIRE DATE | C2: 45819
A3: Salesperson Name | C3: LUIS MILLAN
A4: Salesperson # | C4: W909
A5: Payperiod Ending | C5: ='00W603'!C5 -> 46280
C7: DBW | D7: HELIX | E7: HELIX TOOLS | F7: Total
A8: Sales
B9: ='00W603'!B9 -> 46267 | C9: 0 | D9: 0 | E9: 0 | F9: =SUM(C9:E9) -> 0
B10: =+'00W603'!B10 -> 46268 | C10: 0 | D10: 0 | E10: 0 | F10: =SUM(C10:E10) -> 0
B11: ='00W603'!B11 -> 46269 | C11: 0 | D11: 0 | E11: 0 | F11: =SUM(C11:E11) -> 0
B12: ='00W603'!B12 -> 46272 | C12: 0 | D12: 0 | E12: 0 | F12: =SUM(C12:E12) -> 0
B13: ='00W603'!B13 -> 46273 | C13: 0 | D13: 0 | E13: 0 | F13: =SUM(C13:E13) -> 0
B14: ='00W603'!B14 -> 46274 | C14: 44.6775 | D14: 0 | E14: 0 | F14: =SUM(C14:E14) -> 44.6775
B15: ='00W603'!B15 -> 46275 | C15: 8.1 | D15: 0 | E15: 0 | F15: =SUM(C15:E15) -> 8.1
B16: ='00W603'!B16 -> 46276 | C16: 0 | D16: 0 | E16: 0 | F16: =SUM(C16:E16) -> 0
B17: =+'00W603'!B17 -> 46279 | C17: 0 | D17: 0 | E17: 0 | F17: =SUM(C17:E17) -> 0
B18: ='00W603'!B18 -> 46280 | C18: 970.655 | D18: 0 | E18: 0 | F18: =SUM(C18:E18) -> 970.655
B19: =+'00W603'!B19 -> Extra 1
B20: =+'00W603'!B20 -> Extra 2
B21: Extra 3
B22: Extra 4
B23: Extra 5
B24: Total | C24: =SUM(C9:C23) -> 1023.4325 | D24: =SUM(D9:D23) -> 0 | E24: =SUM(E9:E23) -> 0 | F24: =SUM(F9:F23) -> 1023.4325
A26: Returns
A27: Cust # | B27: Inv #
F28: 0
F29: 0
F30: 0
F31: 0
F32: =SUM(F28:F31) -> 0
A34: 120 Day Chews
A35: Cust # | B35: Inv #
F37: 0
F38: 0
F39: 0
F40: 0
F41: 0
F42: =SUM(F36:F41) -> 0
A43: Adjustments
A44: Cust # | B44: Inv #
A45: Reserve | F45: 0
F46: 0
F47: 0
F48: 0
F49: 0
F50: =SUM(F45:F49) -> 0
E54: Grand Total | F54: =+F24+F32+F42+F50 -> 1023.4325
A56: RESERVE: | B56: BB | C56: -9.64
B57: Add | C57: 52.5
B58: EB | C58: =+C56+C57 -> 42.86
A60: Guarantee
A61: 15
B62: Hours | C62: Pay | D62: Hours | E62: Pay
B63: Week1 | C63: Week1 | D63: Week2 | E63: Week2 | F63: Total
A64: Regular | B64: 0 | C64: =A61*B64 -> 0 | D64: 0 | E64: =+D64*A61 -> 0 | F64: =+C64+E64 -> 0
A65: Overtime | C65: =A61*B65*1.5 -> 0 | D65: 0 | E65: =A61*D65*1.5 -> 0 | F65: =+C65+E65 -> 0
A66: Total | B66: =+B64+B65 -> 0 | C66: =+C64+C65 -> 0 | D66: =+D64+D65 -> 0 | E66: =+E64+E65 -> 0 | F66: =+F64+F65 -> 0
A68: Deductions on hold
A69: J&J2026 | B69: 634917 | C69: PWWGP - NO COMMISSION AFTER 12/15/26 | F69: 768.56

Sheet 00W849
A1: SALES COMMISSION RECAP
A2: HIRE DATE | C2: 44669
A3: Salesman Name | C3: John Baemmert
A4: Salesman # | C4: 00W849
A5: Payperiod Ending | C5: =+'00W603'!C5 -> 46280
C7: DBW | D7: HELIX | E7: HELIX TOOLS | F7: Total
A8: Sales
B9: ='00W603'!B9 -> 46267 | C9: 0 | D9: 0 | E9: 0 | F9: =SUM(C9:E9) -> 0
B10: =+'00W603'!B10 -> 46268 | C10: 599.95 | D10: 0 | E10: 0 | F10: =SUM(C10:E10) -> 599.95
B11: ='00W603'!B11 -> 46269 | C11: 97.7377 | D11: 0 | E11: 0 | F11: =SUM(C11:E11) -> 97.7377
B12: ='00W603'!B12 -> 46272 | C12: 0 | D12: 0 | E12: 0 | F12: =SUM(C12:E12) -> 0
B13: ='00W603'!B13 -> 46273 | C13: 0 | D13: 0 | E13: 0 | F13: =SUM(C13:E13) -> 0
B14: ='00W603'!B14 -> 46274 | C14: 0 | D14: 0 | E14: 0 | F14: =SUM(C14:E14) -> 0
B15: ='00W603'!B15 -> 46275 | C15: 0 | D15: 0 | E15: 0 | F15: =SUM(C15:E15) -> 0
B16: ='00W603'!B16 -> 46276 | C16: 0 | D16: 0 | E16: 0 | F16: =SUM(C16:E16) -> 0
B17: ='00W603'!B17 -> 46279 | C17: 74.35 | D17: 0 | E17: 0 | F17: =SUM(C17:E17) -> 74.35
B18: ='00W603'!B18 -> 46280 | C18: 0 | D18: 0 | E18: 0 | F18: =SUM(C18:E18) -> 0
B19: =+'00W603'!B19 -> Extra 1
B20: =+'00W603'!B20 -> Extra 2
B21: Extra 3
B22: Extra 4
B23: Extra 5
B24: Total | C24: =SUM(C9:C23) -> 772.0377 | D24: =SUM(D9:D23) -> 0 | E24: =SUM(E9:E23) -> 0 | F24: =SUM(F9:F23) -> 772.0377
A26: Returns
A27: Cust # | B27: Inv #
F28: 0
F29: 0
F30: 0
F31: =SUM(F28:F30) -> 0
A33: 120 Day Chews
A34: Cust # | B34: Inv #
A35: MSY2025 | B35: 627887 | F35: -75
F36: 0
F37: 0
F38: 0
F39: =SUM(F35:F38) -> -75
A40: Adjustments
A41: Cust # | B41: Inv #
A42: DPD2026 | B42: 629580 | C42: PWWGP 50% - paid in full 9/8/26 | F42: 497.77
A43: EDD2026 | B43: 629756 | C43: PWWGP 50%-paid with CBP 9/15/26 | F43: 492.84
F44: 0
F45: 0
F46: 0
F47: 0
F48: =SUM(F42:F47) -> 990.61
E52: Grand Total | F52: =+F24+F31+F39+F48 -> 1687.6477
A54: RESERVE: | B54: FULL
A58: Guarantee
A59: 15
B60: Hours | C60: Pay | D60: Hours | E60: Pay
B61: Week1 | C61: Week1 | D61: Week2 | E61: Week2 | F61: Total
A62: Regular | B62: 25.75 | C62: =A59*B62 -> 386.25 | D62: 25.5 | E62: =+D62*A59 -> 382.5 | F62: =+C62+E62 -> 768.75
A63: Overtime | C63: =A59*B63*1.5 -> 0 | E63: =A59*D63*1.5 -> 0 | F63: =+C63+E63 -> 0
A64: Total | B64: =+B62+B63 -> 25.75 | C64: =+C62+C63 -> 386.25 | D64: =+D62+D63 -> 25.5 | E64: =+E62+E63 -> 382.5 | F64: =+F62+F63 -> 768.75
A66: Deductions on hold

Sheet 00W930
A1: SALES COMMISSION RECAP
A2: Start Date | C2: 43164
A3: Salesman Name | C3: ADAM MISUREK
A4: Salesman # | C4: W930
A5: Payperiod Ending | C5: =+'00W603'!C5 -> 46280
E6: COMMISSIONS
C7: DBW | D7: HELIX | E7: MISC | F7: Total
A8: Sales
B9: ='00W603'!B9 -> 46267 | C9: 692.47 | D9: 0 | E9: 0 | F9: =SUM(C9:E9) -> 692.47
B10: ='00W603'!B10 -> 46268 | C10: 27.1775 | D10: 0 | E10: 0 | F10: =SUM(C10:E10) -> 27.1775
B11: ='00W603'!B11 -> 46269 | C11: 0 | D11: 0 | E11: 0 | F11: =SUM(C11:E11) -> 0
B12: ='00W603'!B12 -> 46272 | C12: 0 | D12: 0 | E12: 0 | F12: =SUM(C12:E12) -> 0
B13: ='00W603'!B13 -> 46273 | C13: 0 | D13: 0 | E13: 0 | F13: =SUM(C13:E13) -> 0
B14: ='00W603'!B14 -> 46274 | C14: 780 | D14: 0 | E14: 0 | F14: =SUM(C14:E14) -> 780
B15: ='00W603'!B15 -> 46275 | C15: 209.196 | D15: 0 | E15: 0 | F15: =SUM(C15:E15) -> 209.196
B16: ='00W603'!B16 -> 46276 | C16: 229.125 | D16: 0 | E16: 0 | F16: =SUM(C16:E16) -> 229.125
B17: =+'00W603'!B17 -> 46279 | C17: 0 | D17: 0 | E17: 0 | F17: =SUM(C17:E17) -> 0
B18: ='00W603'!B18 -> 46280 | C18: 774.845 | D18: 0 | E18: 0 | F18: =SUM(C18:E18) -> 774.845
B19: =+'00W603'!B19 -> Extra 1
B20: =+'00W603'!B20 -> Extra 2
B21: Extra 3
B22: Extra 4
B23: Extra 5
B24: Total | C24: =SUM(C9:C23) -> 2712.8135 | D24: =SUM(D9:D23) -> 0 | E24: =SUM(E9:E23) -> 0 | F24: =SUM(F9:F23) -> 2712.8135
A26: Returns
A27: Cust # | B27: Inv #
F28: 0
F29: 0
F30: 0
F31: 0
F32: =SUM(F28:F31) -> 0
A34: 120 day chews
A35: Cust # | B35: Inv #
F36: 0
F37: 0
F38: 0
F39: 0
F40: =SUM(F36:F39) -> 0
A41: Adjustments
F42: 0
F43: 0
F44: 0
F45: 0
F46: 0
F47: 0
F48: =SUM(F42:F47) -> 0
E51: Grand Total | F51: =+F24+F32+F40+F48 -> 2712.8135
A52: Reserve: | B52: Full
A54: 15
B55: Hours | C55: Pay | D55: Hours | E55: Pay
B56: Week1 | C56: Week1 | D56: Week2 | E56: Week2 | F56: Total
A57: Regular | B57: 0 | C57: =A54*B57 -> 0 | D57: 0 | E57: =A54*D57 -> 0 | F57: =+C57+E57 -> 0
A58: Overtime | C58: =A54*B58*1.5 -> 0 | D58: 0 | E58: =A54*D58*1.5 -> 0 | F58: =+C58+E58 -> 0
A59: Total | B59: =+B57+B58 -> 0 | C59: =+C57+C58 -> 0 | D59: =+D57+D58 -> 0 | E59: =+E57+E58 -> 0 | F59: =+F57+F58 -> 0
A61: Deductions on hold

Sheet 00W934
A1: SALES COMMISSION RECAP
A2: HIRE DATE | C2: 45825
A3: Salesman Name | C3: Les Kubeny
A4: Salesman # | C4: W934
A5: Payperiod Ending | C5: ='00W603'!C5 -> 46280
C7: DBW | D7: HELIX | E7: HELIX TOOLS | F7: Total
A8: Sales
B9: ='00W603'!B9 -> 46267 | C9: 0 | D9: 0 | E9: 0 | F9: =SUM(C9:E9) -> 0
B10: =+'00W603'!B10 -> 46268 | C10: 0 | D10: 0 | E10: 0 | F10: =SUM(C10:E10) -> 0
B11: ='00W603'!B11 -> 46269 | C11: 0 | D11: 0 | E11: 0 | F11: =SUM(C11:E11) -> 0
B12: ='00W603'!B12 -> 46272 | C12: 0 | D12: 0 | E12: 0 | F12: =SUM(C12:E12) -> 0
B13: ='00W603'!B13 -> 46273 | C13: 0 | D13: 0 | E13: 0 | F13: =SUM(C13:E13) -> 0
B14: ='00W603'!B14 -> 46274 | C14: 187.11 | D14: 0 | E14: 0 | F14: =SUM(C14:E14) -> 187.11
B15: ='00W603'!B15 -> 46275 | C15: 0 | D15: 0 | E15: 0 | F15: =SUM(C15:E15) -> 0
B16: ='00W603'!B16 -> 46276 | C16: 1.38 | D16: 0 | E16: 0 | F16: =SUM(C16:E16) -> 1.38
B17: =+'00W603'!B17 -> 46279 | C17: 0 | D17: 0 | E17: 0 | F17: =SUM(C17:E17) -> 0
B18: ='00W603'!B18 -> 46280 | C18: 0 | D18: 0 | E18: 0 | F18: =SUM(C18:E18) -> 0
B19: =+'00W603'!B19 -> Extra 1
B20: =+'00W603'!B20 -> Extra 2
B21: Extra 3
B22: Extra 4
B23: Extra 5
B24: Total | C24: =SUM(C9:C23) -> 188.49 | D24: =SUM(D9:D23) -> 0 | E24: =SUM(E9:E23) -> 0 | F24: =SUM(F9:F23) -> 188.49
A26: Returns
A27: Cust # | B27: Inv #
F28: 0
F29: 0
F30: 0
F31: 0
F32: =SUM(F28:F31) -> 0
A34: 120 Day Chews
A35: Cust # | B35: Inv #
F36: 0
F37: 0
F38: 0
F39: 0
F40: 0
F41: 0
F42: =SUM(F36:F41) -> 0
A43: Adjustments
A44: Cust # | B44: Inv #
A45: Reserve | F45: 0
F46: 0
F47: 0
F48: 0
F49: 0
F50: =SUM(F45:F49) -> 0
E54: Grand Total | F54: =+F24+F32+F42+F50 -> 188.49
A56: RESERVE: | B56: BB | C56: 96
B57: Add | C57: =267.17 -> 267.17 | D57: TLA2024 | E57: 614995 | F57: PWWGP - PAID IN FULL 12/15/25
B58: ADD | C58: 12.99 | D58: PAYCHECK 2/2/26
B59: Add | C59: 5.4 | D59: Paycheck 3/17/26
B60: Add | C60: 41.79 | D60: Paycheck 6/23/26
B61: Add | C61: 76.65 | D61: Returned Direct Deposit - 1/21 payroll
B62: EB | C62: =SUM(C56:C61) -> 500
A64: Guarantee
A65: 15
B66: Hours | C66: Pay | D66: Hours | E66: Pay
B67: Week1 | C67: Week1 | D67: Week2 | E67: Week2 | F67: Total
A68: Regular | B68: 7 | C68: =A65*B68 -> 105 | D68: 12 | E68: =+D68*A65 -> 180 | F68: =+C68+E68 -> 285
A69: Overtime | C69: =A65*B69*1.5 -> 0 | D69: 0 | E69: =A65*D69*1.5 -> 0 | F69: =+C69+E69 -> 0
A70: Total | B70: =+B68+B69 -> 7 | C70: =+C68+C69 -> 105 | D70: =+D68+D69 -> 12 | E70: =+E68+E69 -> 180 | F70: =+F68+F69 -> 285
A72: Deductions on hold

Sheet 00W938
A1: SALES COMMISSION RECAP
A2: HIRE DATE | C2: 1/6/25 - REHIRE
A3: Salesperson Name | C3: GEOFFREY NURSE
A4: Salesperson # | C4: W938
A5: Payperiod Ending | C5: ='00W603'!C5 -> 46280
C7: DBW | D7: HELIX | E7: HELIX TOOLS | F7: Total
A8: Sales
B9: ='00W603'!B9 -> 46267 | C9: 0 | D9: 0 | E9: 0 | F9: =SUM(C9:E9) -> 0
B10: =+'00W603'!B10 -> 46268 | C10: 0 | D10: 0 | E10: 0 | F10: =SUM(C10:E10) -> 0
B11: ='00W603'!B11 -> 46269 | C11: 0 | D11: 0 | E11: 0 | F11: =SUM(C11:E11) -> 0
B12: ='00W603'!B12 -> 46272 | C12: 0 | D12: 0 | E12: 0 | F12: =SUM(C12:E12) -> 0
B13: ='00W603'!B13 -> 46273 | C13: 0 | D13: 0 | E13: 0 | F13: =SUM(C13:E13) -> 0
B14: ='00W603'!B14 -> 46274 | C14: 0 | D14: 0 | E14: 0 | F14: =SUM(C14:E14) -> 0
B15: ='00W603'!B15 -> 46275 | C15: 0 | D15: 0 | E15: 0 | F15: =SUM(C15:E15) -> 0
B16: ='00W603'!B16 -> 46276 | C16: 0 | D16: 0 | E16: 0 | F16: =SUM(C16:E16) -> 0
B17: =+'00W603'!B17 -> 46279 | C17: 74.35 | D17: 0 | E17: 0 | F17: =SUM(C17:E17) -> 74.35
B18: ='00W603'!B18 -> 46280 | C18: 0 | D18: 0 | E18: 0 | F18: =SUM(C18:E18) -> 0
B19: =+'00W603'!B19 -> Extra 1
B20: =+'00W603'!B20 -> Extra 2
B21: Extra 3
B22: Extra 4
B23: Extra 5
B24: Total | C24: =SUM(C9:C23) -> 74.35 | D24: =SUM(D9:D23) -> 0 | E24: =SUM(E9:E23) -> 0 | F24: =SUM(F9:F23) -> 74.35
A26: Returns
A27: Cust # | B27: Inv #
F28: 0
F29: 0
F30: 0
F31: 0
F32: =SUM(F28:F31) -> 0
A34: 120 Day Chews
A35: Cust # | B35: Inv #
F36: 0
F37: 0
F38: 0
F39: 0
F40: 0
F41: =SUM(F36:F40) -> 0
A42: Adjustments
A43: Cust # | B43: Inv #
A44: Reserve | F44: 0
F45: 0
F46: 0
F47: 0
F48: 0
F49: 0
F50: 0
F51: =SUM(F44:F50) -> 0
E55: Grand Total | F55: =+F24+F32+F41+F51 -> 74.35
A57: RESERVE: | B57: BB | C57: 504.5
B58: Add | C58: 0
B59: EB | C59: =+C57+C58 -> 504.5
A61: Guarantee
A62: 15
B63: Hours | C63: Pay | D63: Hours | E63: Pay
B64: Week1 | C64: Week1 | D64: Week2 | E64: Week2 | F64: Total
A65: Regular | B65: 13.5 | C65: =A62*B65 -> 202.5 | D65: 23.25 | E65: =A62*D65 -> 348.75 | F65: =+C65+E65 -> 551.25
A66: Overtime | C66: =A62*B66*1.5 -> 0 | D66: 0 | E66: =A62*D66*1.5 -> 0 | F66: =+C66+E66 -> 0
A67: Total | B67: =+B65+B66 -> 13.5 | C67: =+C65+C66 -> 202.5 | D67: =+D65+D66 -> 23.25 | E67: =+E65+E66 -> 348.75 | F67: =+F65+F66 -> 551.25
A69: Deductions on hold

Sheet 00W959
A1: SALES COMMISSION RECAP
A2: HIRE DATE | C2: 45936
A3: Salesperson Name | C3: CASSANDRA KOLHOUSE
A4: Salesperson # | C4: W959
A5: Payperiod Ending | C5: ='00W603'!C5 -> 46280
C7: DBW | D7: HELIX | E7: HELIX TOOLS | F7: Total
A8: Sales
B9: ='00W603'!B9 -> 46267 | C9: 41.18 | D9: 0 | E9: 0 | F9: =SUM(C9:E9) -> 41.18
B10: =+'00W603'!B10 -> 46268 | C10: 126.61 | D10: 0 | E10: 0 | F10: =SUM(C10:E10) -> 126.61
B11: ='00W603'!B11 -> 46269 | C11: 109.36 | D11: 0 | E11: 0 | F11: =SUM(C11:E11) -> 109.36
B12: ='00W603'!B12 -> 46272 | C12: 0 | D12: 0 | E12: 0 | F12: =SUM(C12:E12) -> 0
B13: ='00W603'!B13 -> 46273 | C13: 0 | D13: 0 | E13: 0 | F13: =SUM(C13:E13) -> 0
B14: ='00W603'!B14 -> 46274 | C14: 0 | D14: 0 | E14: 0 | F14: =SUM(C14:E14) -> 0
B15: ='00W603'!B15 -> 46275 | C15: 485.605 | D15: 0 | E15: 0 | F15: =SUM(C15:E15) -> 485.605
B16: ='00W603'!B16 -> 46276 | C16: 0 | D16: 0 | E16: 0 | F16: =SUM(C16:E16) -> 0
B17: =+'00W603'!B17 -> 46279 | C17: 0 | D17: 0 | E17: 0 | F17: =SUM(C17:E17) -> 0
B18: ='00W603'!B18 -> 46280 | C18: 0 | D18: 0 | E18: 0 | F18: =SUM(C18:E18) -> 0
B19: =+'00W603'!B19 -> Extra 1
B20: =+'00W603'!B20 -> Extra 2
B21: Extra 3
B22: Extra 4
B23: Extra 5
B24: Total | C24: =SUM(C9:C23) -> 762.755 | D24: =SUM(D9:D23) -> 0 | E24: =SUM(E9:E23) -> 0 | F24: =SUM(F9:F23) -> 762.755
A26: Returns
A27: Cust # | B27: Inv #
F28: 0
F29: 0
F30: 0
F31: 0
F32: =SUM(F28:F31) -> 0
A34: 120 Day Chews
A35: Cust # | B35: Inv #
F36: 0
F37: 0
F38: 0
F39: 0
F40: 0
F41: 0
F42: =SUM(F36:F41) -> 0
A43: Adjustments
A44: Cust # | B44: Inv #
A45: Reserve | F45: 0
A46: See below | F46: -200
F47: 0
F48: 0
F49: 0
F50: =SUM(F45:F49) -> -200
E54: Grand Total | F54: =+F24+F32+F42+F50 -> 562.755
A56: RESERVE: | B56: BB | C56: 275
B57: Add | C57: 0
B58: EB | C58: =+C56+C57 -> 275
A60: Guarantee
A61: 15
B62: Hours | C62: Pay | D62: Hours | E62: Pay
B63: Week1 | C63: Week1 | D63: Week2 | E63: Week2 | F63: Total
A64: Regular | B64: 23.25 | C64: =A61*B64 -> 348.75 | D64: 20.25 | E64: =+D64*A61 -> 303.75 | F64: =+C64+E64 -> 652.5
A65: Overtime | C65: =A61*B65*1.5 -> 0 | D65: 0 | E65: =A61*D65*1.5 -> 0 | F65: =+C65+E65 -> 0
A66: Total | B66: =+B64+B65 -> 23.25 | C66: =+C64+C65 -> 348.75 | D66: =+D64+D65 -> 20.25 | E66: =+E64+E65 -> 303.75 | F66: =+F64+F65 -> 652.5
A68: Deductions on hold
A69: NXT2026 | B69: 629700 | C69: PWWGP 50% - NO COMMISSION AFTER 9/20/26 | F69: 691.51
A70: JDMA1 | B70: 634673 | C70: PWWGP 50% - NO COMMISSION AFTER 12/10/26 | F70: 485.61
A74: PRG2026 | B74: 630464 | C74: return | F74: -995.93
E75: Taken 8/18 | F75: 95.93
E76: Balance | F76: =+F74+F75 -> -900
E77: Taken 9/1 | F77: 200
E78: Balance | F78: =+F76+F77 -> -700
E79: Taken 9/15 | F79: 200
E80: Balance | F80: =+F78+F79 -> -500

Sheet 00W962
A1: SALES COMMISSION RECAP
A2: HIRE DATE | C2: 45960
A3: Salesperson Name | C3: CHRISTOPHER KUSSROW
A4: Salesperson # | C4: W962
A5: Payperiod Ending | C5: ='00W603'!C5 -> 46280
C7: DBW | D7: HELIX | E7: HELIX TOOLS | F7: Total
A8: Sales
B9: ='00W603'!B9 -> 46267 | C9: 71.6794 | D9: 0 | E9: 0 | F9: =SUM(C9:E9) -> 71.6794
B10: =+'00W603'!B10 -> 46268 | C10: 0 | D10: 0 | E10: 0 | F10: =SUM(C10:E10) -> 0
B11: ='00W603'!B11 -> 46269 | C11: 245.7825 | D11: 0 | E11: 0 | F11: =SUM(C11:E11) -> 245.7825
B12: ='00W603'!B12 -> 46272 | C12: 0 | D12: 0 | E12: 0 | F12: =SUM(C12:E12) -> 0
B13: ='00W603'!B13 -> 46273 | C13: 405 | D13: 0 | E13: 0 | F13: =SUM(C13:E13) -> 405
B14: ='00W603'!B14 -> 46274 | C14: 67.5 | D14: 0 | E14: 0 | F14: =SUM(C14:E14) -> 67.5
B15: ='00W603'!B15 -> 46275 | C15: 0 | D15: 0 | E15: 0 | F15: =SUM(C15:E15) -> 0
B16: ='00W603'!B16 -> 46276 | C16: 0 | D16: 0 | E16: 0 | F16: =SUM(C16:E16) -> 0
B17: =+'00W603'!B17 -> 46279 | C17: 0 | D17: 0 | E17: 0 | F17: =SUM(C17:E17) -> 0
B18: ='00W603'!B18 -> 46280 | C18: 62.5 | D18: 0 | E18: 0 | F18: =SUM(C18:E18) -> 62.5
B19: =+'00W603'!B19 -> Extra 1
B20: =+'00W603'!B20 -> Extra 2
B21: Extra 3
B22: Extra 4
B23: Extra 5
B24: Total | C24: =SUM(C9:C23) -> 852.4619 | D24: =SUM(D9:D23) -> 0 | E24: =SUM(E9:E23) -> 0 | F24: =SUM(F9:F23) -> 852.4619
A26: Returns
A27: Cust # | B27: Inv #
A28: CGC2933 | B28: 629901 | F28: -22.5
A29: CRL2020 | B29: 633667 | F29: -405
F30: 0
F31: 0
F32: =SUM(F28:F31) -> -427.5
A34: 120 Day Chews
A35: Cust # | B35: Inv #
A36: AJD1380 | B36: 628389 | F36: -18.25
F37: 0
F38: 0
F39: 0
F40: 0
F41: 0
F42: =SUM(F36:F41) -> -18.25
A43: Adjustments
A44: Cust # | B44: Inv #
A45: Reserve | F45: 0
F46: 0
F47: 0
F48: 0
F49: 0
F50: =SUM(F45:F49) -> 0
E54: Grand Total | F54: =+F24+F32+F42+F50 -> 406.7119
A56: RESERVE: | B56: BB | C56: 325
B57: Add | C57: 0
B58: EB | C58: =+C56+C57 -> 325
A60: Guarantee
A61: 15
B62: Hours | C62: Pay | D62: Hours | E62: Pay
B63: Week1 | C63: Week1 | D63: Week2 | E63: Week2 | F63: Total
A64: Regular | B64: 31.25 | C64: =A61*B64 -> 468.75 | D64: 29.5 | E64: =+D64*A61 -> 442.5 | F64: =+C64+E64 -> 911.25
A65: Overtime | C65: =A61*B65*1.5 -> 0 | D65: 0 | E65: =A61*D65*1.5 -> 0 | F65: =+C65+E65 -> 0
A66: Total | B66: =+B64+B65 -> 31.25 | C66: =+C64+C65 -> 468.75 | D66: =+D64+D65 -> 29.5 | E66: =+E64+E65 -> 442.5 | F66: =+F64+F65 -> 911.25
A68: Deductions on hold

Sheet 00W973
A1: SALES COMMISSION RECAP
A2: HIRE DATE | C2: 43887
A3: Salesman Name | C3: ANTHONY SUTTON
A4: Salesman # | C4: 00W973
A5: Payperiod Ending | C5: ='00W603'!C5 -> 46280
C7: DBW | D7: HELIX | E7: MISC | F7: Total
A8: Sales
B9: ='00W603'!B9 -> 46267 | C9: 0 | D9: 0 | E9: 0 | F9: =SUM(C9:E9) -> 0
B10: =+'00W603'!B10 -> 46268 | C10: 0 | D10: 0 | E10: 0 | F10: =SUM(C10:E10) -> 0
B11: ='00W603'!B11 -> 46269 | C11: 0 | D11: 0 | E11: 0 | F11: =SUM(C11:E11) -> 0
B12: ='00W603'!B12 -> 46272 | C12: 0 | D12: 0 | E12: 0 | F12: =SUM(C12:E12) -> 0
B13: ='00W603'!B13 -> 46273 | C13: 0 | D13: 0 | E13: 0 | F13: =SUM(C13:E13) -> 0
B14: ='00W603'!B14 -> 46274 | C14: 0 | D14: 0 | E14: 0 | F14: =SUM(C14:E14) -> 0
B15: ='00W603'!B15 -> 46275 | C15: 1022.5707 | D15: 0 | E15: 0 | F15: =SUM(C15:E15) -> 1022.5707
B16: ='00W603'!B16 -> 46276 | C16: 0 | D16: 0 | E16: 0 | F16: =SUM(C16:E16) -> 0
B17: ='00W603'!B17 -> 46279 | C17: 0 | D17: 0 | E17: 0 | F17: =SUM(C17:E17) -> 0
B18: ='00W603'!B18 -> 46280 | C18: 210.92 | D18: 0 | E18: 0 | F18: =SUM(C18:E18) -> 210.92
B19: =+'00W603'!B19 -> Extra 1
B20: =+'00W603'!B20 -> Extra 2
B21: Extra 3
B22: Extra 4
B23: Extra 5
B24: Total | C24: =SUM(C9:C23) -> 1233.4907 | D24: =SUM(D9:D23) -> 0 | E24: =SUM(E9:E23) -> 0 | F24: =SUM(F9:F23) -> 1233.4907
A26: Returns
A27: Cust # | B27: Inv #
F28: 0
F29: 0
F30: 0
F31: 0
F32: =SUM(F28:F31) -> 0
A34: 120 Day Chews
A35: Cust # | B35: Inv #
F36: 0
F37: 0
F38: 0
F39: 0
F40: 0
F41: =SUM(F36:F40) -> 0
A42: Adjustments
A43: Cust # | B43: Inv #
A44: Reserve | F44: 0
F45: 0
F46: 0
F47: 0
F48: 0
F49: =SUM(F44:F48) -> 0
E53: Grand Total | F53: =+F24+F32+F41+F49 -> 1233.4907
A54: RESERVE: | B54: FULL | C54: Take 500 more
A55: New Reserve | B55: BB | C55: 300
B56: Add | C56: 0
B57: EB | C57: =+C55+C56 -> 300
A59: Guarantee
A60: 15
B61: Hours | C61: Pay | D61: Hours | E61: Pay
B62: Week1 | C62: Week1 | D62: Week2 | E62: Week2 | F62: Total
B63: 17.5 | C63: =A60*B63 -> 262.5 | D63: 27.5 | E63: =+D63*A60 -> 412.5 | F63: =+C63+E63 -> 675 | G63: NO HOLIDAY PAY - NOT HERE ON 9/4
A64: Overtime | C64: =A60*B64*1.5 -> 0 | E64: =A60*D64*1.5 -> 0 | F64: =+C64+E64 -> 0
A65: Total | B65: =+B63+B64 -> 17.5 | C65: =+C63+C64 -> 262.5 | D65: =+D63+D64 -> 27.5 | E65: =+E63+E64 -> 412.5 | F65: =+F63+F64 -> 675
A67: Deductions on hold
A68: LA2024 | B68: 627945 | C68: customer paid $1,900 9-15-26 ~ wait for it to show before applying the chew | F68: -1068.4
C69: Hold until 9/30/26

Sheet 00W983
A1: SALES COMMISSION RECAP
A2: HIRE DATE | C2: 44067
A3: Salesman Name | C3: SCOTT TOPORSH
A4: Salesman # | C4: W983
A5: Payperiod Ending | C5: =+'00W603'!C5 -> 46280
C7: DBW | D7: HELIX | E7: HELIX TOOLS | F7: Total
A8: Sales
B9: ='00W603'!B9 -> 46267 | C9: 0 | D9: 0 | E9: 0 | F9: =SUM(C9:E9) -> 0
B10: =+'00W603'!B10 -> 46268 | C10: 66.96 | D10: 0 | E10: 0 | F10: =SUM(C10:E10) -> 66.96
B11: ='00W603'!B11 -> 46269 | C11: 1173.2 | D11: 0 | E11: 0 | F11: =SUM(C11:E11) -> 1173.2
B12: ='00W603'!B12 -> 46272 | C12: 0 | D12: 0 | E12: 0 | F12: =SUM(C12:E12) -> 0
B13: ='00W603'!B13 -> 46273 | C13: 0 | D13: 0 | E13: 0 | F13: =SUM(C13:E13) -> 0
B14: ='00W603'!B14 -> 46274 | C14: 67.5 | D14: 0 | E14: 0 | F14: =SUM(C14:E14) -> 67.5
B15: ='00W603'!B15 -> 46275 | C15: 0 | D15: 0 | E15: 0 | F15: =SUM(C15:E15) -> 0
B16: ='00W603'!B16 -> 46276 | C16: 712.05 | D16: 0 | E16: 0 | F16: =SUM(C16:E16) -> 712.05
B17: =+'00W603'!B17 -> 46279 | C17: 253.0238 | D17: 0 | E17: 0 | F17: =SUM(C17:E17) -> 253.0238
B18: ='00W603'!B18 -> 46280 | C18: 0 | D18: 0 | E18: 0 | F18: =SUM(C18:E18) -> 0
B19: =+'00W603'!B19 -> Extra 1
B20: =+'00W603'!B20 -> Extra 2
B21: Extra 3
B22: Extra 4
B23: Extra 5
B24: Total | C24: =SUM(C9:C23) -> 2272.7338 | D24: =SUM(D9:D23) -> 0 | E24: =SUM(E9:E23) -> 0 | F24: =SUM(F9:F23) -> 2272.7338
A26: Returns
A27: Cust # | B27: Inv #
A28: CGC2933 | B28: 629901 | F28: -90
A29: MID4444 | B29: 633991 | F29: -253.14
F30: 0
F31: 0
F32: =SUM(F28:F31) -> -343.14
A34: 120 Day Chews
A35: Cust # | B35: Inv #
F36: 0
F37: 0
F38: 0
F39: 0
F40: 0
F41: =SUM(F36:F40) -> 0
A42: Adjustments
A43: Cust # | B43: Inv #
F44: 0
F45: 0
F46: 0
F47: 0
F48: 0
F49: 0
F50: =SUM(F44:F49) -> 0
A54: RESERVE | B54: FULL | C54: 500 | E54: Grand Total | F54: =+F24+F32+F41+F50 -> 1929.5938
A62: Guarantee | B62: Hours | C62: Pay | D62: Hours | E62: Pay
A63: 15 | B63: Week1 | C63: Week1 | D63: Week2 | E63: Week2 | F63: Total
A64: Regular | B64: 25.75 | C64: =A63*B64 -> 386.25 | D64: 33.25 | E64: =+D64*A63 -> 498.75 | F64: =+C64+E64 -> 885
A65: Overtime | B65: 0 | C65: =A63*B65*1.5 -> 0 | D65: 0 | E65: =A63*D65*1.5 -> 0 | F65: =+C65+E65 -> 0
A66: Total | B66: =+B64+B65 -> 25.75 | C66: =+C64+C65 -> 386.25 | D66: =+D64+D65 -> 33.25 | E66: =+E64+E65 -> 498.75 | F66: =+F64+F65 -> 885
A70: Deductions on hold
A71: GUT2022 | B71: 633319 | C71: PWWGP - NO COMMISSION AFTER 11/18/26 | F71: 416.52
